atlas/__init__.py
atlas/app/__init__.py
atlas/app/base.py
atlas/app/gui.py
atlas/app/thirdparty/__init__.py
atlas/app/thirdparty/maya.py
atlas/app/thirdparty/unreal.py
atlas/context/__init__.py
atlas/mixins/__init__.py
atlas/mixins/maya.py
atlas/mixins/unreal.py
atlas_framework-0.1.7.dist-info/LICENSE
atlas_framework-0.1.7.dist-info/METADATA
atlas_framework-0.1.7.dist-info/WHEEL
atlas_framework-0.1.7.dist-info/top_level.txt
atlas_framework-0.1.7.dist-info/RECORD
